TutorialspointShujukuJiaocheng20160127/README.md
TutorialspointShujukuJiaocheng20160127/__init__.py
TutorialspointShujukuJiaocheng20160127/__main__.py
TutorialspointShujukuJiaocheng20160127/file.epub
TutorialspointShujukuJiaocheng20160127/index.html
TutorialspointShujukuJiaocheng20160127/css/__init__.py
TutorialspointShujukuJiaocheng20160127/css/annotations.css
TutorialspointShujukuJiaocheng20160127/css/main.css
TutorialspointShujukuJiaocheng20160127/css/normalize.css
TutorialspointShujukuJiaocheng20160127/css/popup.css
TutorialspointShujukuJiaocheng20160127/font/__init__.py
TutorialspointShujukuJiaocheng20160127/font/fontello.eot
TutorialspointShujukuJiaocheng20160127/font/fontello.svg
TutorialspointShujukuJiaocheng20160127/font/fontello.ttf
TutorialspointShujukuJiaocheng20160127/font/fontello.woff
TutorialspointShujukuJiaocheng20160127/img/__init__.py
TutorialspointShujukuJiaocheng20160127/img/annotator-glyph-sprite.png
TutorialspointShujukuJiaocheng20160127/img/annotator-icon-sprite.png
TutorialspointShujukuJiaocheng20160127/img/apple-touch-icon.png
TutorialspointShujukuJiaocheng20160127/img/cancelfullscreen.png
TutorialspointShujukuJiaocheng20160127/img/close.png
TutorialspointShujukuJiaocheng20160127/img/fullscreen.png
TutorialspointShujukuJiaocheng20160127/img/loader.gif
TutorialspointShujukuJiaocheng20160127/img/menu-icon.png
TutorialspointShujukuJiaocheng20160127/img/save.png
TutorialspointShujukuJiaocheng20160127/img/saved.png
TutorialspointShujukuJiaocheng20160127/img/settings-s.png
TutorialspointShujukuJiaocheng20160127/img/settings.png
TutorialspointShujukuJiaocheng20160127/img/star.png
TutorialspointShujukuJiaocheng20160127/js/__init__.py
TutorialspointShujukuJiaocheng20160127/js/epub.js
TutorialspointShujukuJiaocheng20160127/js/epub.min.js
TutorialspointShujukuJiaocheng20160127/js/epub.min.map
TutorialspointShujukuJiaocheng20160127/js/hooks.min.js
TutorialspointShujukuJiaocheng20160127/js/hooks.min.map
tutorialspoint_shujuku_jiaocheng_20160127-2024.2.29.0.dist-info/METADATA
tutorialspoint_shujuku_jiaocheng_20160127-2024.2.29.0.dist-info/WHEEL
tutorialspoint_shujuku_jiaocheng_20160127-2024.2.29.0.dist-info/entry_points.txt
tutorialspoint_shujuku_jiaocheng_20160127-2024.2.29.0.dist-info/top_level.txt
tutorialspoint_shujuku_jiaocheng_20160127-2024.2.29.0.dist-info/RECORD
